sense_django/__init__.py
sense_django/admin.py
sense_django/apps.py
sense_django/base_model.py
sense_django/middleware.py
sense_django/models.py
sense_django/request_utils.py
sense_django/services.py
sense_django/tests.py
sense_django/utils.py
sense_django/views.py
sense_django-0.2.26.dist-info/METADATA
sense_django-0.2.26.dist-info/WHEEL
sense_django-0.2.26.dist-info/top_level.txt
sense_django-0.2.26.dist-info/RECORD
