Metadata-Version: 2.1
Name: sense-django
Version: 0.2.26
Summary: sense django
Home-page: UNKNOWN
Author: kafka0102
Author-email: yujianjia@sensedeal.ai
License: BSD License
Platform: UNKNOWN
Classifier: Environment :: Web Environment
Classifier: Framework :: Django
Classifier: Framework :: Django :: 2.1
Classifier: Intended Audience :: Developers
Classifier: License :: OSI Approved :: BSD License
Classifier: Operating System :: OS Independent
Classifier: Programming Language :: Python
Classifier: Programming Language :: Python :: 3.5
Classifier: Programming Language :: Python :: 3.6
Classifier: Topic :: Internet :: WWW/HTTP
Classifier: Topic :: Internet :: WWW/HTTP :: Dynamic Content
Requires-Dist: sense-core (>=0.1.4)
Requires-Dist: numpy (>=1.15)
Requires-Dist: pypinyin (>=0.33.1)
